{
  "examType": "Timed Assessment",
  "subject": "Computers",
  "classNum": "4",
  "title": "Timed Assessment - Computers",
  "teacher": "Venkata Vishnu",
  "assessmentFormat": "mcq",
  "startDateTime": "2026-06-15T09:00:00.000Z",
  "endDateTime": "2026-06-15T10:00:00.000Z",
  "description": "A sample timed assessment for Class 4 Computers",
  "totalQuestions": 5,
  "totalMarks": 5,
  "timeLimitMinutes": 30,
  "wrongAnswerPenaltyFraction": 0,
  "preassessmentsecretkey": "",
  "secretKey": "",
  "teacherSecretKey": "",
  "sections": [
    { "range": "1-5", "marks": 1 }
  ],
  "questions": [
    {
      "question": "What does CPU stand for?",
      "options": ["Central Processing Unit", "Computer Personal Unit", "Central Process Unit", "Control Processing Unit"],
      "answer": 0,
      "difficulty": "easy"
    },
    {
      "question": "Which device is used to store data permanently?",
      "options": ["RAM", "Hard Drive", "CPU", "Monitor"],
      "answer": 1,
      "difficulty": "easy"
    },
    {
      "question": "What is an output device?",
      "options": ["Keyboard", "Mouse", "Monitor", "Microphone"],
      "answer": 2,
      "difficulty": "easy"
    },
    {
      "question": "Which key is used to delete text?",
      "options": ["Shift", "Delete", "Enter", "Space"],
      "answer": 1,
      "difficulty": "easy"
    },
    {
      "question": "What is the brain of the computer?",
      "options": ["RAM", "CPU", "Hard Drive", "GPU"],
      "answer": 1,
      "difficulty": "easy"
    }
  ]
}
